{
  "generated": "2026-06-24T04:14:10Z",
  "source": "build_elos.py — FIFA-rank prior, calibrated to odds.json",
  "sims": 100000,
  "params": {
    "suprK": 0.42,
    "total": 2.65,
    "floor": 0.18,
    "pensK": 0.9,
    "atkCoef": 0.05,
    "defCoef": 0.05,
    "formOppCoef": 0.4,
    "formCap": 0.4,
    "formAtkFloor": 1.0,
    "formDefFloor": 0.0,
    "rankCoef": 0.04,
    "rankCoefGroup": 0.15,
    "pensHangover": 0.06,
    "finalScoreBoost": 1.2,
    "koTotalMul": 0.85,
    "etTotal": 0.75,
    "dcRho": -0.3,
    "nudgeK": 0.55
  },
  "ratings": {
    "Mexico": 0.5338,
    "South Korea": -0.4521,
    "South Africa": -0.6954,
    "Czechia": 0.1921,
    "Canada": -0.7982,
    "Switzerland": -0.3403,
    "Qatar": -0.7046,
    "Bosnia and Herzegovina": 0.1124,
    "Brazil": 1.2191,
    "Morocco": 0.5848,
    "Haiti": -0.7125,
    "Scotland": -0.8042,
    "United States": 0.9469,
    "Paraguay": -1.1028,
    "Australia": -0.7975,
    "Türkiye": -0.7125,
    "Germany": 1.1547,
    "Curaçao": -0.5733,
    "Côte d'Ivoire": -0.2624,
    "Ecuador": -0.11,
    "Netherlands": 1.3579,
    "Japan": 0.5076,
    "Sweden": -0.3156,
    "Tunisia": -0.7125,
    "Belgium": 0.1997,
    "Egypt": -0.61,
    "Iran": -1.2321,
    "New Zealand": -0.807,
    "Spain": 1.8258,
    "Cabo Verde": -0.5949,
    "Saudi Arabia": -0.7871,
    "Uruguay": -0.291,
    "France": 2.2503,
    "Senegal": 0.2022,
    "Norway": 0.7057,
    "Iraq": 0.9054,
    "Argentina": 1.6683,
    "Algeria": -1.2424,
    "Austria": -0.7152,
    "Jordan": -0.7125,
    "Portugal": 1.4621,
    "Colombia": 0.2649,
    "DR Congo": 0.2912,
    "Uzbekistan": -0.2358,
    "England": 1.696,
    "Croatia": -0.2371,
    "Panama": -0.7125,
    "Ghana": -0.8094
  },
  "calibrated": {
    "Mexico": 0.5338,
    "South Korea": -0.4521,
    "South Africa": -0.6954,
    "Czechia": 0.1921,
    "Canada": -0.7982,
    "Switzerland": -0.3403,
    "Qatar": -0.7046,
    "Bosnia and Herzegovina": 0.1124,
    "Brazil": 1.2191,
    "Morocco": 0.5848,
    "Haiti": -0.7125,
    "Scotland": -0.8042,
    "United States": 0.9469,
    "Paraguay": -1.1028,
    "Australia": -0.7975,
    "Türkiye": -0.7125,
    "Germany": 1.1547,
    "Curaçao": -0.5733,
    "Côte d'Ivoire": -0.2624,
    "Ecuador": -0.11,
    "Netherlands": 1.3579,
    "Japan": 0.5076,
    "Sweden": -0.3156,
    "Tunisia": -0.7125,
    "Belgium": 0.1997,
    "Egypt": -0.61,
    "Iran": -1.2321,
    "New Zealand": -0.807,
    "Spain": 1.8258,
    "Cabo Verde": -0.5949,
    "Saudi Arabia": -0.7871,
    "Uruguay": -0.291,
    "France": 2.2503,
    "Senegal": 0.2022,
    "Norway": 0.7057,
    "Iraq": 0.9054,
    "Argentina": 1.6683,
    "Algeria": -1.2424,
    "Austria": -0.7152,
    "Jordan": -0.7125,
    "Portugal": 1.4621,
    "Colombia": 0.2649,
    "DR Congo": 0.2912,
    "Uzbekistan": -0.2358,
    "England": 1.696,
    "Croatia": -0.2371,
    "Panama": -0.7125,
    "Ghana": -0.8094
  },
  "baselineProb": {
    "Mexico": 0.019571,
    "South Korea": 0.00233,
    "South Africa": 0.000466,
    "Czechia": 0.00466,
    "Canada": 0.00233,
    "Switzerland": 0.005126,
    "Qatar": 0.000466,
    "Bosnia and Herzegovina": 0.00466,
    "Brazil": 0.046132,
    "Morocco": 0.017707,
    "Haiti": 0.000466,
    "Scotland": 0.001398,
    "United States": 0.044268,
    "Paraguay": 0.000466,
    "Australia": 0.001398,
    "Türkiye": 0.000466,
    "Germany": 0.050326,
    "Curaçao": 0.000466,
    "Côte d'Ivoire": 0.003262,
    "Ecuador": 0.001398,
    "Netherlands": 0.061976,
    "Japan": 0.016309,
    "Sweden": 0.00233,
    "Tunisia": 0.000466,
    "Belgium": 0.009786,
    "Egypt": 0.00233,
    "Iran": 0.000466,
    "New Zealand": 0.000466,
    "Spain": 0.123952,
    "Cabo Verde": 0.001398,
    "Saudi Arabia": 0.000466,
    "Uruguay": 0.00233,
    "France": 0.191519,
    "Senegal": 0.003262,
    "Norway": 0.027493,
    "Iraq": 0.00466,
    "Argentina": 0.132805,
    "Algeria": 0.000466,
    "Austria": 0.001398,
    "Jordan": 0.000466,
    "Portugal": 0.084343,
    "Colombia": 0.017241,
    "DR Congo": 0.00466,
    "Uzbekistan": 0.000466,
    "England": 0.095527,
    "Croatia": 0.004194,
    "Panama": 0.000466,
    "Ghana": 0.001398
  },
  "canon": {
    "Mexico": "Mexico",
    "South Korea": "South Korea",
    "South Africa": "South Africa",
    "Czechia": "Czechia",
    "Canada": "Canada",
    "Switzerland": "Switzerland",
    "Qatar": "Qatar",
    "Bosnia and Herzegovina": "Bosnia and Herzegovina",
    "Brazil": "Brazil",
    "Morocco": "Morocco",
    "Haiti": "Haiti",
    "Scotland": "Scotland",
    "United States": "United States",
    "Paraguay": "Paraguay",
    "Australia": "Australia",
    "Türkiye": "Türkiye",
    "Germany": "Germany",
    "Curaçao": "Curaçao",
    "Côte d'Ivoire": "Côte d'Ivoire",
    "Ecuador": "Ecuador",
    "Netherlands": "Netherlands",
    "Japan": "Japan",
    "Sweden": "Sweden",
    "Tunisia": "Tunisia",
    "Belgium": "Belgium",
    "Egypt": "Egypt",
    "Iran": "Iran",
    "New Zealand": "New Zealand",
    "Spain": "Spain",
    "Cabo Verde": "Cabo Verde",
    "Saudi Arabia": "Saudi Arabia",
    "Uruguay": "Uruguay",
    "France": "France",
    "Senegal": "Senegal",
    "Norway": "Norway",
    "Iraq": "Iraq",
    "Argentina": "Argentina",
    "Algeria": "Algeria",
    "Austria": "Austria",
    "Jordan": "Jordan",
    "Portugal": "Portugal",
    "Colombia": "Colombia",
    "DR Congo": "DR Congo",
    "Uzbekistan": "Uzbekistan",
    "England": "England",
    "Croatia": "Croatia",
    "Panama": "Panama",
    "Ghana": "Ghana"
  },
  "modelChamp": {
    "Mexico": 0.02045,
    "South Korea": 0.00308,
    "South Africa": 0.00074,
    "Czechia": 0.00396,
    "Canada": 0.00178,
    "Switzerland": 0.00471,
    "Qatar": 0.00048,
    "Bosnia and Herzegovina": 0.00435,
    "Brazil": 0.04763,
    "Morocco": 0.01898,
    "Haiti": 0.0,
    "Scotland": 0.00116,
    "United States": 0.04349,
    "Paraguay": 0.00052,
    "Australia": 0.00146,
    "Türkiye": 0.0,
    "Germany": 0.05127,
    "Curaçao": 0.00065,
    "Côte d'Ivoire": 0.00305,
    "Ecuador": 0.00142,
    "Netherlands": 0.06014,
    "Japan": 0.01558,
    "Sweden": 0.00295,
    "Tunisia": 0.0,
    "Belgium": 0.01018,
    "Egypt": 0.00263,
    "Iran": 0.00041,
    "New Zealand": 0.00069,
    "Spain": 0.12734,
    "Cabo Verde": 0.0016,
    "Saudi Arabia": 0.00065,
    "Uruguay": 0.00203,
    "France": 0.18686,
    "Senegal": 0.00313,
    "Norway": 0.02783,
    "Iraq": 0.00567,
    "Argentina": 0.13297,
    "Algeria": 0.00066,
    "Austria": 0.00154,
    "Jordan": 0.0,
    "Portugal": 0.08363,
    "Colombia": 0.01633,
    "DR Congo": 0.00492,
    "Uzbekistan": 0.00044,
    "England": 0.0955,
    "Croatia": 0.00555,
    "Panama": 0.0,
    "Ghana": 0.00159
  }
}