{
  "generated": "2026-06-24T15:03:41Z",
  "source": "build_elos.py — FIFA-rank prior, calibrated to odds.json",
  "sims": 100000,
  "params": {
    "suprK": 0.42,
    "total": 2.65,
    "floor": 0.18,
    "pensK": 0.9,
    "atkCoef": 0.05,
    "defCoef": 0.05,
    "formOppCoef": 0.4,
    "formCap": 0.4,
    "formAtkFloor": 1.0,
    "formDefFloor": 0.0,
    "rankCoef": 0.04,
    "rankCoefGroup": 0.15,
    "pensHangover": 0.06,
    "finalScoreBoost": 1.2,
    "koTotalMul": 0.85,
    "etTotal": 0.75,
    "dcRho": -0.3,
    "nudgeK": 0.55
  },
  "ratings": {
    "Mexico": 0.4852,
    "South Korea": -0.4238,
    "South Africa": -0.6427,
    "Czechia": 0.2641,
    "Canada": -0.7228,
    "Switzerland": -0.1566,
    "Qatar": -0.6145,
    "Bosnia and Herzegovina": 0.2599,
    "Brazil": 1.2304,
    "Morocco": 0.606,
    "Haiti": -1.5747,
    "Scotland": -0.5422,
    "United States": 0.9806,
    "Paraguay": -1.1168,
    "Australia": -0.7879,
    "Türkiye": -0.2469,
    "Germany": 1.1849,
    "Curaçao": -0.6305,
    "Côte d'Ivoire": -0.2032,
    "Ecuador": -0.0925,
    "Netherlands": 1.3977,
    "Japan": 0.5761,
    "Sweden": -0.6801,
    "Tunisia": -0.9845,
    "Belgium": 0.3184,
    "Egypt": -0.6032,
    "Iran": -1.0652,
    "New Zealand": -0.7368,
    "Spain": 1.863,
    "Cabo Verde": -1.2217,
    "Saudi Arabia": -0.8441,
    "Uruguay": -0.0749,
    "France": 2.2548,
    "Senegal": 0.2151,
    "Norway": 0.7211,
    "Iraq": 0.7751,
    "Argentina": 1.7086,
    "Algeria": -1.3293,
    "Austria": -0.5131,
    "Jordan": -1.299,
    "Portugal": 1.5015,
    "Colombia": 0.4012,
    "DR Congo": 0.3533,
    "Uzbekistan": 0.011,
    "England": 1.7716,
    "Croatia": -0.2545,
    "Panama": -0.6822,
    "Ghana": -0.8362
  },
  "calibrated": {
    "Mexico": 0.4852,
    "South Korea": -0.4238,
    "South Africa": -0.6427,
    "Czechia": 0.2641,
    "Canada": -0.7228,
    "Switzerland": -0.1566,
    "Qatar": -0.6145,
    "Bosnia and Herzegovina": 0.2599,
    "Brazil": 1.2304,
    "Morocco": 0.606,
    "Haiti": -1.5747,
    "Scotland": -0.5422,
    "United States": 0.9806,
    "Paraguay": -1.1168,
    "Australia": -0.7879,
    "Türkiye": -0.2469,
    "Germany": 1.1849,
    "Curaçao": -0.6305,
    "Côte d'Ivoire": -0.2032,
    "Ecuador": -0.0925,
    "Netherlands": 1.3977,
    "Japan": 0.5761,
    "Sweden": -0.6801,
    "Tunisia": -0.9845,
    "Belgium": 0.3184,
    "Egypt": -0.6032,
    "Iran": -1.0652,
    "New Zealand": -0.7368,
    "Spain": 1.863,
    "Cabo Verde": -1.2217,
    "Saudi Arabia": -0.8441,
    "Uruguay": -0.0749,
    "France": 2.2548,
    "Senegal": 0.2151,
    "Norway": 0.7211,
    "Iraq": 0.7751,
    "Argentina": 1.7086,
    "Algeria": -1.3293,
    "Austria": -0.5131,
    "Jordan": -1.299,
    "Portugal": 1.5015,
    "Colombia": 0.4012,
    "DR Congo": 0.3533,
    "Uzbekistan": 0.011,
    "England": 1.7716,
    "Croatia": -0.2545,
    "Panama": -0.6822,
    "Ghana": -0.8362
  },
  "baselineProb": {
    "Mexico": 0.01831,
    "South Korea": 0.002347,
    "South Africa": 0.000469,
    "Czechia": 0.004695,
    "Canada": 0.002347,
    "Switzerland": 0.005164,
    "Qatar": 0.000469,
    "Bosnia and Herzegovina": 0.004695,
    "Brazil": 0.046479,
    "Morocco": 0.01831,
    "Haiti": 0.0,
    "Scotland": 0.001408,
    "United States": 0.04554,
    "Paraguay": 0.000469,
    "Australia": 0.001408,
    "Türkiye": 0.0,
    "Germany": 0.050235,
    "Curaçao": 0.000469,
    "Côte d'Ivoire": 0.003286,
    "Ecuador": 0.001408,
    "Netherlands": 0.060094,
    "Japan": 0.016901,
    "Sweden": 0.001408,
    "Tunisia": 0.0,
    "Belgium": 0.010798,
    "Egypt": 0.002347,
    "Iran": 0.000469,
    "New Zealand": 0.000469,
    "Spain": 0.125352,
    "Cabo Verde": 0.000469,
    "Saudi Arabia": 0.000469,
    "Uruguay": 0.002347,
    "France": 0.188732,
    "Senegal": 0.002347,
    "Norway": 0.026761,
    "Iraq": 0.004695,
    "Argentina": 0.13615,
    "Algeria": 0.000469,
    "Austria": 0.001408,
    "Jordan": 0.0,
    "Portugal": 0.08216,
    "Colombia": 0.018779,
    "DR Congo": 0.004695,
    "Uzbekistan": 0.000469,
    "England": 0.099061,
    "Croatia": 0.004225,
    "Panama": 0.0,
    "Ghana": 0.001408
  },
  "canon": {
    "Mexico": "Mexico",
    "South Korea": "South Korea",
    "South Africa": "South Africa",
    "Czechia": "Czechia",
    "Canada": "Canada",
    "Switzerland": "Switzerland",
    "Qatar": "Qatar",
    "Bosnia and Herzegovina": "Bosnia and Herzegovina",
    "Brazil": "Brazil",
    "Morocco": "Morocco",
    "Haiti": "Haiti",
    "Scotland": "Scotland",
    "United States": "United States",
    "Paraguay": "Paraguay",
    "Australia": "Australia",
    "Türkiye": "Türkiye",
    "Germany": "Germany",
    "Curaçao": "Curaçao",
    "Côte d'Ivoire": "Côte d'Ivoire",
    "Ecuador": "Ecuador",
    "Netherlands": "Netherlands",
    "Japan": "Japan",
    "Sweden": "Sweden",
    "Tunisia": "Tunisia",
    "Belgium": "Belgium",
    "Egypt": "Egypt",
    "Iran": "Iran",
    "New Zealand": "New Zealand",
    "Spain": "Spain",
    "Cabo Verde": "Cabo Verde",
    "Saudi Arabia": "Saudi Arabia",
    "Uruguay": "Uruguay",
    "France": "France",
    "Senegal": "Senegal",
    "Norway": "Norway",
    "Iraq": "Iraq",
    "Argentina": "Argentina",
    "Algeria": "Algeria",
    "Austria": "Austria",
    "Jordan": "Jordan",
    "Portugal": "Portugal",
    "Colombia": "Colombia",
    "DR Congo": "DR Congo",
    "Uzbekistan": "Uzbekistan",
    "England": "England",
    "Croatia": "Croatia",
    "Panama": "Panama",
    "Ghana": "Ghana"
  },
  "modelChamp": {
    "Mexico": 0.01803,
    "South Korea": 0.00285,
    "South Africa": 0.00072,
    "Czechia": 0.00486,
    "Canada": 0.00214,
    "Switzerland": 0.0063,
    "Qatar": 0.00063,
    "Bosnia and Herzegovina": 0.00491,
    "Brazil": 0.04614,
    "Morocco": 0.01769,
    "Haiti": 0.0,
    "Scotland": 0.00166,
    "United States": 0.04434,
    "Paraguay": 0.00056,
    "Australia": 0.00151,
    "Türkiye": 0.0,
    "Germany": 0.05078,
    "Curaçao": 0.00044,
    "Côte d'Ivoire": 0.00303,
    "Ecuador": 0.00133,
    "Netherlands": 0.06023,
    "Japan": 0.01685,
    "Sweden": 0.00121,
    "Tunisia": 0.0,
    "Belgium": 0.01194,
    "Egypt": 0.00236,
    "Iran": 0.00068,
    "New Zealand": 0.0006,
    "Spain": 0.12363,
    "Cabo Verde": 0.00036,
    "Saudi Arabia": 0.00054,
    "Uruguay": 0.00295,
    "France": 0.18239,
    "Senegal": 0.00265,
    "Norway": 0.02673,
    "Iraq": 0.0046,
    "Argentina": 0.13942,
    "Algeria": 0.0004,
    "Austria": 0.00208,
    "Jordan": 0.0,
    "Portugal": 0.08319,
    "Colombia": 0.01929,
    "DR Congo": 0.00476,
    "Uzbekistan": 0.00059,
    "England": 0.09905,
    "Croatia": 0.00428,
    "Panama": 0.0,
    "Ghana": 0.0013
  }
}