{
  "generated": "2026-07-17T17:41:48.878332Z",
  "sims": 1000000,
  "standings": [
    {
      "name": "Pete",
      "odds": 0.59608,
      "base": 0.5961,
      "delta": -2e-05,
      "teams": [
        {
          "name": "Spain",
          "odds": 0.59608,
          "base": 0.5961,
          "delta": -2e-05
        },
        {
          "name": "Japan",
          "odds": 0.0,
          "base": 0.00328,
          "delta": -0.00328
        },
        {
          "name": "Paraguay",
          "odds": 0.0,
          "base": 0.00075,
          "delta": -0.00075
        }
      ],
      "rank": 1
    },
    {
      "name": "Nik",
      "odds": 0.40392,
      "base": 0.4039,
      "delta": 2e-05,
      "teams": [
        {
          "name": "Argentina",
          "odds": 0.40392,
          "base": 0.4039,
          "delta": 2e-05
        },
        {
          "name": "Mexico",
          "odds": 0.0,
          "base": 0.00302,
          "delta": -0.00302
        },
        {
          "name": "Czechia",
          "odds": 0.0,
          "base": 0.00063,
          "delta": -0.00063
        }
      ],
      "rank": 2
    },
    {
      "name": "Agatha",
      "odds": 0.0,
      "base": 0.00048,
      "delta": -0.00048,
      "teams": [
        {
          "name": "Morocco",
          "odds": 0.0,
          "base": 0.0009,
          "delta": -0.0009
        },
        {
          "name": "Australia",
          "odds": 0.0,
          "base": 0.00031,
          "delta": -0.00031
        },
        {
          "name": "Iraq",
          "odds": 0.0,
          "base": 0.0006,
          "delta": -0.0006
        }
      ],
      "rank": 3
    },
    {
      "name": "Charlie",
      "odds": 0.0,
      "base": 0.01276,
      "delta": -0.01276,
      "teams": [
        {
          "name": "Colombia",
          "odds": 0.0,
          "base": 0.01276,
          "delta": -0.01276
        },
        {
          "name": "South Korea",
          "odds": 0.0,
          "base": 6e-05,
          "delta": -6e-05
        },
        {
          "name": "Saudi Arabia",
          "odds": 0.0,
          "base": 3e-05,
          "delta": -3e-05
        },
        {
          "name": "Jordan",
          "odds": 0.0,
          "base": 2e-05,
          "delta": -2e-05
        }
      ],
      "rank": 3
    },
    {
      "name": "Charlotte",
      "odds": 0.0,
      "base": 0.00029,
      "delta": -0.00029,
      "teams": [
        {
          "name": "Netherlands",
          "odds": 0.0,
          "base": 0.03506,
          "delta": -0.03506
        },
        {
          "name": "Norway",
          "odds": 0.0,
          "base": 0.00029,
          "delta": -0.00029
        },
        {
          "name": "Ghana",
          "odds": 0.0,
          "base": 0.00013,
          "delta": -0.00013
        }
      ],
      "rank": 3
    },
    {
      "name": "Darcy",
      "odds": 0.0,
      "base": 0.22181,
      "delta": -0.22181,
      "teams": [
        {
          "name": "France",
          "odds": 0.0,
          "base": 0.22181,
          "delta": -0.22181
        },
        {
          "name": "United States",
          "odds": 0.0,
          "base": 0.01689,
          "delta": -0.01689
        },
        {
          "name": "Tunisia",
          "odds": 0.0,
          "base": 1e-05,
          "delta": -1e-05
        },
        {
          "name": "Haiti",
          "odds": 0.0,
          "base": 0.0,
          "delta": null
        }
      ],
      "rank": 3
    },
    {
      "name": "Iva",
      "odds": 0.0,
      "base": 0.00011,
      "delta": -0.00011,
      "teams": [
        {
          "name": "Uruguay",
          "odds": 0.0,
          "base": 0.00017,
          "delta": -0.00017
        },
        {
          "name": "Türkiye",
          "odds": 0.0,
          "base": 0.0,
          "delta": null
        },
        {
          "name": "Qatar",
          "odds": 0.0,
          "base": 1e-05,
          "delta": -1e-05
        }
      ],
      "rank": 3
    },
    {
      "name": "Kelly",
      "odds": 0.0,
      "base": 0.05783,
      "delta": -0.05783,
      "teams": [
        {
          "name": "Portugal",
          "odds": 0.0,
          "base": 0.06182,
          "delta": -0.06182
        },
        {
          "name": "Austria",
          "odds": 0.0,
          "base": 0.0002,
          "delta": -0.0002
        },
        {
          "name": "Canada",
          "odds": 0.0,
          "base": 0.00127,
          "delta": -0.00127
        }
      ],
      "rank": 3
    },
    {
      "name": "Mat",
      "odds": 0.0,
      "base": 0.17464,
      "delta": -0.17464,
      "teams": [
        {
          "name": "England",
          "odds": 0.0,
          "base": 0.17464,
          "delta": -0.17464
        },
        {
          "name": "Switzerland",
          "odds": 0.0,
          "base": 0.00255,
          "delta": -0.00255
        },
        {
          "name": "Algeria",
          "odds": 0.0,
          "base": 8e-05,
          "delta": -8e-05
        }
      ],
      "rank": 3
    },
    {
      "name": "Ondine",
      "odds": 0.0,
      "base": 0.00017,
      "delta": -0.00017,
      "teams": [
        {
          "name": "Senegal",
          "odds": 0.0,
          "base": 0.00029,
          "delta": -0.00029
        },
        {
          "name": "Iran",
          "odds": 0.0,
          "base": 4e-05,
          "delta": -4e-05
        },
        {
          "name": "Uzbekistan",
          "odds": 0.0,
          "base": 7e-05,
          "delta": -7e-05
        },
        {
          "name": "Curaçao",
          "odds": 0.0,
          "base": 1e-05,
          "delta": -1e-05
        }
      ],
      "rank": 3
    },
    {
      "name": "Paul",
      "odds": 0.0,
      "base": 0.01127,
      "delta": -0.01127,
      "teams": [
        {
          "name": "Belgium",
          "odds": 0.0,
          "base": 0.0159,
          "delta": -0.0159
        },
        {
          "name": "Côte d'Ivoire",
          "odds": 0.0,
          "base": 6e-05,
          "delta": -6e-05
        },
        {
          "name": "Panama",
          "odds": 0.0,
          "base": 2e-05,
          "delta": -2e-05
        },
        {
          "name": "Cabo Verde",
          "odds": 0.0,
          "base": 0.00081,
          "delta": -0.00081
        }
      ],
      "rank": 3
    },
    {
      "name": "Sydney",
      "odds": 0.0,
      "base": 0.04365,
      "delta": -0.04365,
      "teams": [
        {
          "name": "Brazil",
          "odds": 0.0,
          "base": 0.05058,
          "delta": -0.05058
        },
        {
          "name": "Ecuador",
          "odds": 0.0,
          "base": 0.00059,
          "delta": -0.00059
        },
        {
          "name": "South Africa",
          "odds": 0.0,
          "base": 3e-05,
          "delta": -3e-05
        },
        {
          "name": "Scotland",
          "odds": 0.0,
          "base": 0.00012,
          "delta": -0.00012
        }
      ],
      "rank": 3
    },
    {
      "name": "Tom",
      "odds": 0.0,
      "base": 0.00539,
      "delta": -0.00539,
      "teams": [
        {
          "name": "Croatia",
          "odds": 0.0,
          "base": 0.00115,
          "delta": -0.00115
        },
        {
          "name": "Egypt",
          "odds": 0.0,
          "base": 0.00539,
          "delta": -0.00539
        },
        {
          "name": "DR Congo",
          "odds": 0.0,
          "base": 0.00055,
          "delta": -0.00055
        }
      ],
      "rank": 3
    },
    {
      "name": "Tomi",
      "odds": 0.0,
      "base": 0.00056,
      "delta": -0.00056,
      "teams": [
        {
          "name": "Germany",
          "odds": 0.0,
          "base": 5e-05,
          "delta": -5e-05
        },
        {
          "name": "Sweden",
          "odds": 0.0,
          "base": 4e-05,
          "delta": -4e-05
        },
        {
          "name": "Bosnia and Herzegovina",
          "odds": 0.0,
          "base": 0.00078,
          "delta": -0.00078
        },
        {
          "name": "New Zealand",
          "odds": 0.0,
          "base": 2e-05,
          "delta": -2e-05
        }
      ],
      "rank": 3
    }
  ]
}