{
  "generated": "2026-07-03T20:01:06.542848Z",
  "sims": 1000000,
  "standings": [
    {
      "name": "Darcy",
      "odds": 0.35678,
      "base": 0.36129,
      "delta": -0.00451,
      "teams": [
        {
          "name": "France",
          "odds": 0.36214,
          "base": 0.36212,
          "delta": 2e-05
        },
        {
          "name": "United States",
          "odds": 0.01806,
          "base": 0.01945,
          "delta": -0.00139
        },
        {
          "name": "Tunisia",
          "odds": 0.0,
          "base": 1e-05,
          "delta": -1e-05
        },
        {
          "name": "Haiti",
          "odds": 0.0,
          "base": 0.0,
          "delta": null
        }
      ],
      "rank": 1
    },
    {
      "name": "Nik",
      "odds": 0.32529,
      "base": 0.32622,
      "delta": -0.00093,
      "teams": [
        {
          "name": "Argentina",
          "odds": 0.22976,
          "base": 0.23384,
          "delta": -0.00408
        },
        {
          "name": "Mexico",
          "odds": 0.0378,
          "base": 0.03722,
          "delta": 0.00058
        },
        {
          "name": "Czechia",
          "odds": 0.0,
          "base": 0.00063,
          "delta": -0.00063
        }
      ],
      "rank": 2
    },
    {
      "name": "Pete",
      "odds": 0.10594,
      "base": 0.10328,
      "delta": 0.00266,
      "teams": [
        {
          "name": "Spain",
          "odds": 0.1255,
          "base": 0.12256,
          "delta": 0.00294
        },
        {
          "name": "Paraguay",
          "odds": 0.0008,
          "base": 0.00082,
          "delta": -2e-05
        },
        {
          "name": "Japan",
          "odds": 0.0,
          "base": 0.00328,
          "delta": -0.00328
        }
      ],
      "rank": 3
    },
    {
      "name": "Mat",
      "odds": 0.07268,
      "base": 0.07001,
      "delta": 0.00267,
      "teams": [
        {
          "name": "England",
          "odds": 0.0547,
          "base": 0.05205,
          "delta": 0.00265
        },
        {
          "name": "Switzerland",
          "odds": 0.00548,
          "base": 0.0056,
          "delta": -0.00012
        },
        {
          "name": "Algeria",
          "odds": 0.0,
          "base": 8e-05,
          "delta": -8e-05
        }
      ],
      "rank": 4
    },
    {
      "name": "Kelly",
      "odds": 0.05411,
      "base": 0.05434,
      "delta": -0.00023,
      "teams": [
        {
          "name": "Portugal",
          "odds": 0.06087,
          "base": 0.06145,
          "delta": -0.00058
        },
        {
          "name": "Canada",
          "odds": 0.00124,
          "base": 0.00106,
          "delta": 0.00018
        },
        {
          "name": "Austria",
          "odds": 0.0,
          "base": 0.0002,
          "delta": -0.0002
        }
      ],
      "rank": 5
    },
    {
      "name": "Sydney",
      "odds": 0.04605,
      "base": 0.04488,
      "delta": 0.00117,
      "teams": [
        {
          "name": "Brazil",
          "odds": 0.05437,
          "base": 0.05364,
          "delta": 0.00073
        },
        {
          "name": "Ecuador",
          "odds": 0.0,
          "base": 0.00059,
          "delta": -0.00059
        },
        {
          "name": "South Africa",
          "odds": 0.0,
          "base": 3e-05,
          "delta": -3e-05
        },
        {
          "name": "Scotland",
          "odds": 0.0,
          "base": 0.00012,
          "delta": -0.00012
        }
      ],
      "rank": 6
    },
    {
      "name": "Agatha",
      "odds": 0.01494,
      "base": 0.015,
      "delta": -6e-05,
      "teams": [
        {
          "name": "Morocco",
          "odds": 0.02005,
          "base": 0.02057,
          "delta": -0.00052
        },
        {
          "name": "Australia",
          "odds": 0.00031,
          "base": 0.00019,
          "delta": 0.00012
        },
        {
          "name": "Iraq",
          "odds": 0.0,
          "base": 0.0006,
          "delta": -0.0006
        }
      ],
      "rank": 7
    },
    {
      "name": "Charlie",
      "odds": 0.01098,
      "base": 0.0117,
      "delta": -0.00072,
      "teams": [
        {
          "name": "Colombia",
          "odds": 0.01342,
          "base": 0.01415,
          "delta": -0.00073
        },
        {
          "name": "South Korea",
          "odds": 0.0,
          "base": 6e-05,
          "delta": -6e-05
        },
        {
          "name": "Saudi Arabia",
          "odds": 0.0,
          "base": 3e-05,
          "delta": -3e-05
        },
        {
          "name": "Jordan",
          "odds": 0.0,
          "base": 2e-05,
          "delta": -2e-05
        }
      ],
      "rank": 8
    },
    {
      "name": "Charlotte",
      "odds": 0.00647,
      "base": 0.0068,
      "delta": -0.00033,
      "teams": [
        {
          "name": "Norway",
          "odds": 0.00668,
          "base": 0.00728,
          "delta": -0.0006
        },
        {
          "name": "Ghana",
          "odds": 0.0002,
          "base": 0.00012,
          "delta": 8e-05
        },
        {
          "name": "Netherlands",
          "odds": 0.0,
          "base": 0.03506,
          "delta": -0.03506
        }
      ],
      "rank": 9
    },
    {
      "name": "Paul",
      "odds": 0.00608,
      "base": 0.00603,
      "delta": 5e-05,
      "teams": [
        {
          "name": "Belgium",
          "odds": 0.00766,
          "base": 0.00689,
          "delta": 0.00077
        },
        {
          "name": "Cabo Verde",
          "odds": 0.00014,
          "base": 0.00045,
          "delta": -0.00031
        },
        {
          "name": "Côte d'Ivoire",
          "odds": 0.0,
          "base": 6e-05,
          "delta": -6e-05
        },
        {
          "name": "Panama",
          "odds": 0.0,
          "base": 2e-05,
          "delta": -2e-05
        }
      ],
      "rank": 10
    },
    {
      "name": "Tom",
      "odds": 0.00067,
      "base": 0.00045,
      "delta": 0.00022,
      "teams": [
        {
          "name": "Egypt",
          "odds": 0.00081,
          "base": 0.00055,
          "delta": 0.00026
        },
        {
          "name": "Croatia",
          "odds": 0.0,
          "base": 0.00115,
          "delta": -0.00115
        },
        {
          "name": "DR Congo",
          "odds": 0.0,
          "base": 0.00055,
          "delta": -0.00055
        }
      ],
      "rank": 11
    },
    {
      "name": "Iva",
      "odds": 0.0,
      "base": 0.00011,
      "delta": -0.00011,
      "teams": [
        {
          "name": "Uruguay",
          "odds": 0.0,
          "base": 0.00017,
          "delta": -0.00017
        },
        {
          "name": "Türkiye",
          "odds": 0.0,
          "base": 0.0,
          "delta": null
        },
        {
          "name": "Qatar",
          "odds": 0.0,
          "base": 1e-05,
          "delta": -1e-05
        }
      ],
      "rank": 12
    },
    {
      "name": "Ondine",
      "odds": 0.0,
      "base": 0.00017,
      "delta": -0.00017,
      "teams": [
        {
          "name": "Senegal",
          "odds": 0.0,
          "base": 0.00029,
          "delta": -0.00029
        },
        {
          "name": "Iran",
          "odds": 0.0,
          "base": 4e-05,
          "delta": -4e-05
        },
        {
          "name": "Uzbekistan",
          "odds": 0.0,
          "base": 7e-05,
          "delta": -7e-05
        },
        {
          "name": "Curaçao",
          "odds": 0.0,
          "base": 1e-05,
          "delta": -1e-05
        }
      ],
      "rank": 12
    },
    {
      "name": "Tomi",
      "odds": 0.0,
      "base": 0.00056,
      "delta": -0.00056,
      "teams": [
        {
          "name": "Germany",
          "odds": 0.0,
          "base": 5e-05,
          "delta": -5e-05
        },
        {
          "name": "Sweden",
          "odds": 0.0,
          "base": 4e-05,
          "delta": -4e-05
        },
        {
          "name": "Bosnia and Herzegovina",
          "odds": 0.0,
          "base": 0.00078,
          "delta": -0.00078
        },
        {
          "name": "New Zealand",
          "odds": 0.0,
          "base": 2e-05,
          "delta": -2e-05
        }
      ],
      "rank": 12
    }
  ]
}