{
  "generated": "2026-06-21T02:12:46.939063Z",
  "sims": 100000,
  "standings": [
    {
      "name": "Darcy",
      "odds": 0.31049,
      "base": 0.30778,
      "delta": 0.00271,
      "teams": [
        {
          "name": "France",
          "odds": 0.25188,
          "base": 0.24969,
          "delta": 0.00219
        },
        {
          "name": "United States",
          "odds": 0.03145,
          "base": 0.03097,
          "delta": 0.00048
        },
        {
          "name": "Tunisia",
          "odds": 0.0,
          "base": 1e-05,
          "delta": -1e-05
        },
        {
          "name": "Haiti",
          "odds": 0.0,
          "base": 0.0,
          "delta": null
        }
      ],
      "rank": 1
    },
    {
      "name": "Nik",
      "odds": 0.19322,
      "base": 0.19327,
      "delta": -5e-05,
      "teams": [
        {
          "name": "Argentina",
          "odds": 0.18136,
          "base": 0.17993,
          "delta": 0.00143
        },
        {
          "name": "Mexico",
          "odds": 0.0062,
          "base": 0.00725,
          "delta": -0.00105
        },
        {
          "name": "Czechia",
          "odds": 0.00064,
          "base": 0.00051,
          "delta": 0.00013
        }
      ],
      "rank": 2
    },
    {
      "name": "Mat",
      "odds": 0.16146,
      "base": 0.15949,
      "delta": 0.00197,
      "teams": [
        {
          "name": "England",
          "odds": 0.17562,
          "base": 0.17317,
          "delta": 0.00245
        },
        {
          "name": "Switzerland",
          "odds": 0.00181,
          "base": 0.00177,
          "delta": 4e-05
        },
        {
          "name": "Algeria",
          "odds": 4e-05,
          "base": 1e-05,
          "delta": 3e-05
        }
      ],
      "rank": 3
    },
    {
      "name": "Pete",
      "odds": 0.11772,
      "base": 0.11754,
      "delta": 0.00018,
      "teams": [
        {
          "name": "Spain",
          "odds": 0.12048,
          "base": 0.1204,
          "delta": 8e-05
        },
        {
          "name": "Japan",
          "odds": 0.00447,
          "base": 0.00357,
          "delta": 0.0009
        },
        {
          "name": "Paraguay",
          "odds": 8e-05,
          "base": 7e-05,
          "delta": 1e-05
        }
      ],
      "rank": 4
    },
    {
      "name": "Charlotte",
      "odds": 0.06823,
      "base": 0.06331,
      "delta": 0.00492,
      "teams": [
        {
          "name": "Netherlands",
          "odds": 0.05551,
          "base": 0.0526,
          "delta": 0.00291
        },
        {
          "name": "Norway",
          "odds": 0.00986,
          "base": 0.01075,
          "delta": -0.00089
        },
        {
          "name": "Ghana",
          "odds": 0.00014,
          "base": 3e-05,
          "delta": 0.00011
        }
      ],
      "rank": 5
    },
    {
      "name": "Kelly",
      "odds": 0.05143,
      "base": 0.0537,
      "delta": -0.00227,
      "teams": [
        {
          "name": "Portugal",
          "odds": 0.04983,
          "base": 0.05424,
          "delta": -0.00441
        },
        {
          "name": "Canada",
          "odds": 0.00096,
          "base": 0.00076,
          "delta": 0.0002
        },
        {
          "name": "Austria",
          "odds": 0.00064,
          "base": 0.00044,
          "delta": 0.0002
        }
      ],
      "rank": 6
    },
    {
      "name": "Tomi",
      "odds": 0.03644,
      "base": 0.04112,
      "delta": -0.00468,
      "teams": [
        {
          "name": "Germany",
          "odds": 0.0366,
          "base": 0.0417,
          "delta": -0.0051
        },
        {
          "name": "Bosnia and Herzegovina",
          "odds": 0.00045,
          "base": 0.00053,
          "delta": -8e-05
        },
        {
          "name": "Sweden",
          "odds": 0.00027,
          "base": 0.00018,
          "delta": 9e-05
        },
        {
          "name": "New Zealand",
          "odds": 0.0,
          "base": 3e-05,
          "delta": -3e-05
        }
      ],
      "rank": 7
    },
    {
      "name": "Sydney",
      "odds": 0.03386,
      "base": 0.03785,
      "delta": -0.00399,
      "teams": [
        {
          "name": "Brazil",
          "odds": 0.04303,
          "base": 0.04246,
          "delta": 0.00057
        },
        {
          "name": "Ecuador",
          "odds": 0.00018,
          "base": 0.00082,
          "delta": -0.00064
        },
        {
          "name": "South Africa",
          "odds": 7e-05,
          "base": 1e-05,
          "delta": 6e-05
        },
        {
          "name": "Scotland",
          "odds": 1e-05,
          "base": 4e-05,
          "delta": -3e-05
        }
      ],
      "rank": 8
    },
    {
      "name": "Agatha",
      "odds": 0.00832,
      "base": 0.0082,
      "delta": 0.00012,
      "teams": [
        {
          "name": "Morocco",
          "odds": 0.00964,
          "base": 0.00937,
          "delta": 0.00027
        },
        {
          "name": "Iraq",
          "odds": 0.00016,
          "base": 0.00018,
          "delta": -2e-05
        },
        {
          "name": "Australia",
          "odds": 0.00015,
          "base": 0.00017,
          "delta": -2e-05
        }
      ],
      "rank": 9
    },
    {
      "name": "Charlie",
      "odds": 0.00771,
      "base": 0.00739,
      "delta": 0.00032,
      "teams": [
        {
          "name": "Colombia",
          "odds": 0.00677,
          "base": 0.00712,
          "delta": -0.00035
        },
        {
          "name": "South Korea",
          "odds": 0.00056,
          "base": 0.00044,
          "delta": 0.00012
        },
        {
          "name": "Saudi Arabia",
          "odds": 7e-05,
          "base": 2e-05,
          "delta": 5e-05
        },
        {
          "name": "Jordan",
          "odds": 0.0,
          "base": 1e-05,
          "delta": -1e-05
        }
      ],
      "rank": 10
    },
    {
      "name": "Paul",
      "odds": 0.00739,
      "base": 0.00628,
      "delta": 0.00111,
      "teams": [
        {
          "name": "Belgium",
          "odds": 0.0063,
          "base": 0.00503,
          "delta": 0.00127
        },
        {
          "name": "Côte d'Ivoire",
          "odds": 0.0004,
          "base": 0.00069,
          "delta": -0.00029
        },
        {
          "name": "Cabo Verde",
          "odds": 7e-05,
          "base": 5e-05,
          "delta": 2e-05
        },
        {
          "name": "Panama",
          "odds": 0.0,
          "base": 2e-05,
          "delta": -2e-05
        }
      ],
      "rank": 11
    },
    {
      "name": "Tom",
      "odds": 0.00227,
      "base": 0.00267,
      "delta": -0.0004,
      "teams": [
        {
          "name": "Croatia",
          "odds": 0.00137,
          "base": 0.00172,
          "delta": -0.00035
        },
        {
          "name": "DR Congo",
          "odds": 0.00058,
          "base": 0.00051,
          "delta": 7e-05
        },
        {
          "name": "Egypt",
          "odds": 0.00038,
          "base": 0.00048,
          "delta": -0.0001
        }
      ],
      "rank": 12
    },
    {
      "name": "Ondine",
      "odds": 0.00093,
      "base": 0.00086,
      "delta": 7e-05,
      "teams": [
        {
          "name": "Senegal",
          "odds": 0.00108,
          "base": 0.00131,
          "delta": -0.00023
        },
        {
          "name": "Iran",
          "odds": 4e-05,
          "base": 5e-05,
          "delta": -1e-05
        },
        {
          "name": "Uzbekistan",
          "odds": 3e-05,
          "base": 1e-05,
          "delta": 2e-05
        },
        {
          "name": "Curaçao",
          "odds": 1e-05,
          "base": 0.0,
          "delta": 1e-05
        }
      ],
      "rank": 13
    },
    {
      "name": "Iva",
      "odds": 0.00051,
      "base": 0.00053,
      "delta": -2e-05,
      "teams": [
        {
          "name": "Uruguay",
          "odds": 0.00076,
          "base": 0.00099,
          "delta": -0.00023
        },
        {
          "name": "Qatar",
          "odds": 5e-05,
          "base": 1e-05,
          "delta": 4e-05
        },
        {
          "name": "Türkiye",
          "odds": 0.0,
          "base": 0.0,
          "delta": null
        }
      ],
      "rank": 14
    }
  ]
}